d3graph/__init__.py
d3graph/d3graph.py
d3graph/examples.py
d3graph/examples_docs.py
d3graph/d3js/d3.v3.js
d3graph/d3js/d3graphscript.js
d3graph/d3js/index.html.j2
d3graph/d3js/style.css
d3graph-2.6.1.dist-info/licenses/LICENSE
d3graph-2.6.1.dist-info/METADATA
d3graph-2.6.1.dist-info/WHEEL
d3graph-2.6.1.dist-info/top_level.txt
d3graph-2.6.1.dist-info/RECORD
