Metadata-Version: 2.4
Name: d3graph
Version: 2.6.1
Summary: Python package to create interactive network based on d3js.
Author-email: Erdogan Taskesen <erdogant@gmail.com>
License: d3graph is distributed with the 3-clause BSD license.
Project-URL: Homepage, https://erdogant.github.io/d3graph
Project-URL: Download, https://github.com/erdogant/d3graph/archive/{version}.tar.gz
Keywords: Python,
Classifier: Programming Language :: Python :: 3
Classifier: License :: OSI Approved :: BSD License
Classifier: Operating System :: OS Independent
Requires-Python: >=3
License-File: LICENSE
Requires-Dist: pandas
Requires-Dist: numpy
Requires-Dist: colourmap
Requires-Dist: networkx>2
Requires-Dist: ismember
Requires-Dist: jinja2
Requires-Dist: packaging
Requires-Dist: markupsafe==2.0.1
Requires-Dist: python-louvain
Requires-Dist: datazets
Dynamic: license-file
